{
  "$schema": "../../schemas/form-config.json",
  "name": "アンケート・満足度調査",
  "description": "顧客満足度やイベント後のフィードバック収集用テンプレート",
  "basicInfo": {
    "title": "{{title}} アンケート",
    "description": "ご回答いただいた内容は今後のサービス改善に活用させていただきます。\n所要時間: 約{{estimatedMinutes}}分"
  },
  "settings": {
    "isQuiz": false,
    "emailCollectionType": "DO_NOT_COLLECT",
    "isPublished": true
  },
  "questions": [
    {
      "title": "全体的な満足度を教えてください",
      "type": "RATING",
      "required": true,
      "ratingScaleLevel": 5,
      "iconType": "STAR"
    },
    {
      "title": "特に良かった点を選択してください（複数選択可）",
      "type": "CHECKBOX",
      "required": false,
      "options": [
        "内容が分かりやすかった",
        "スタッフの対応が良かった",
        "時間配分が適切だった",
        "資料が充実していた",
        "質疑応答の時間が十分だった"
      ],
      "hasOther": true
    },
    {
      "title": "改善してほしい点があれば教えてください",
      "type": "LONG_TEXT",
      "required": false,
      "description": "自由にご記入ください"
    },
    {
      "title": "今後も参加したいと思いますか？",
      "type": "RADIO",
      "required": true,
      "options": [
        "ぜひ参加したい",
        "機会があれば参加したい",
        "どちらとも言えない",
        "あまり参加したくない",
        "参加したくない"
      ]
    },
    {
      "title": "その他、ご意見・ご要望があればお聞かせください",
      "type": "LONG_TEXT",
      "required": false
    }
  ],
  "variables": {
    "title": {
      "description": "アンケート対象（例: イベント名、サービス名）",
      "required": true
    },
    "estimatedMinutes": {
      "description": "回答目安時間（分）",
      "default": "3"
    }
  }
}
